LICENSE
MANIFEST.in
README.md
quicktest.py
settings_test.py
setup.py
django_youtube_api.egg-info/PKG-INFO
django_youtube_api.egg-info/SOURCES.txt
django_youtube_api.egg-info/dependency_links.txt
django_youtube_api.egg-info/not-zip-safe
django_youtube_api.egg-info/pbr.json
django_youtube_api.egg-info/requires.txt
django_youtube_api.egg-info/top_level.txt
youtube_api/__init__.py
youtube_api/__init__.pyc
youtube_api/admin.py
youtube_api/admin.pyc
youtube_api/api.py
youtube_api/api.pyc
youtube_api/factories.py
youtube_api/factories.pyc
youtube_api/models.py
youtube_api/models.pyc
youtube_api/tests.py
youtube_api/tests.pyc